README.md
setup.py
.idea/.gitignore
ARTSyn.egg-info/PKG-INFO
ARTSyn.egg-info/SOURCES.txt
ARTSyn.egg-info/dependency_links.txt
ARTSyn.egg-info/requires.txt
ARTSyn.egg-info/top_level.txt
artsyn/Classifiers.py
artsyn/DataAnimator.py
artsyn/Dataset.py
artsyn/Resamplers.py
artsyn/ResultHandler.py
artsyn/TabularDataset.py
artsyn/TabularTransformer.py
artsyn/Tools.py
artsyn/__init__.py
artsyn/eval.py
artsyn/main_imbalanced.py
artsyn/paths.py
artsyn/generators/GAN_Synthesizer.py
artsyn/generators/__init__.py
artsyn/generators/c_gan.py
artsyn/generators/cbr.py
artsyn/generators/ct_gan.py
artsyn/generators/ctabgan_synthesizer.py
artsyn/generators/ctabgan_transformer.py
artsyn/generators/ctabganplus_synthesizer.py
artsyn/generators/ctabganplus_transformer.py
artsyn/generators/ctd_clusterer.py
artsyn/generators/ctd_discretizer.py
artsyn/generators/ctd_gan.py
artsyn/generators/ctd_gan_tkde_submission.py
artsyn/generators/fctgan_synthesizer.py
artsyn/generators/fctgan_transformer.py
artsyn/generators/fno.py
artsyn/generators/gan_discriminators.py
artsyn/generators/gan_generators.py
artsyn/generators/gmm_gan_subspaces.py
artsyn/generators/sb_gan.py