Metadata-Version: 2.1
Name: ARTSyn
Version: 0.5.2
Summary: Artificial Tabular Data Synthesizers
Home-page: https://github.com/lakritidis/artsyn
Author: Leonidas Akritidis
Author-email: lakritidis@ihu.gr
Maintainer: Leonidas Akritidis
Maintainer-email: lakritidis@ihu.gr
License: Apache
Keywords: tabular data,tabular data synthesis,data engineering,imbalanced data,GAN,VAE,oversampling,machine learning,deep learning
Requires-Dist: numpy
Requires-Dist: pandas
Requires-Dist: matplotlib
Requires-Dist: seaborn
Requires-Dist: joblib
Requires-Dist: sdv
Requires-Dist: torch>=2.0.0
Requires-Dist: scikit-learn>=1.4.0
Requires-Dist: xgboost
Requires-Dist: imblearn>=0.0
Requires-Dist: rdt<2.0,>=1.3.0
Requires-Dist: tqdm
Requires-Dist: timm
